[
    {
        "SClassName": "循環概念店",
        "CityName": "臺東縣",
        "Zipcode": null,
        "AreaName": "臺東市",
        "STypeName": "捐送,買賣",
        "GoodsTypeName": "玩具類,書籍類,舊衣類,其他類,生活用品類",
        "StatusDesc": "營業中",
        "PhotoPath": "202211\\f198e9ba-f749-40fe-8865-72fe418e605f.jpg",
        "StoreId_enc": "dEgu92RwW+6dh/WMClKHgnjDsUPTilDclLdmsxBPS/PGwUxNiSs7KFQYPRKW6z0F",
        "storeid": "bcd41852-a033-46a6-a8f8-62587b5aa381",
        "sname": "社團法人臺東縣智障者家長協會",
        "sclass": 2,
        "citycode": "V",
        "CodeZipIdx": 337,
        "addr": "中興路二段200巷7號",
        "lat": 22.769241,
        "lon": 121.128962,
        "phoneclass": null,
        "phone": "08-923-8668",
        "stype": null,
        "goodstype": 227,
        "lineUrl": null,
        "memo": null,
        "status": 1,
        "updateid": null,
        "InsertDT": null,
        "UpdateDT": null,
        "SiteUrl": null,
        "IsWebSite": false,
        "IsCollege": false,
        "ApprovalNumber": null
    },
    {
        "SClassName": "循環概念店",
        "CityName": "臺東縣",
        "Zipcode": null,
        "AreaName": "臺東市",
        "STypeName": "捐送,買賣",
        "GoodsTypeName": "玩具類,3C用品類,家具類,電器類,舊衣類,其他類,生活用品類",
        "StatusDesc": "營業中",
        "PhotoPath": "202211\\b3f687d8-b0ef-4359-aabf-945d128966f9.jpg",
        "StoreId_enc": "7VFh1j3JiEYERJBh9+AqNjJUQuxDTVnbUTbNEmQJU2GsFZj1aKamM101G9f1fc0T",
        "storeid": "cc4dc59f-e24c-4f56-a880-61898281d62b",
        "sname": "碰運氣二手雜貨舖",
        "sclass": 2,
        "citycode": "V",
        "CodeZipIdx": 337,
        "addr": "和平街198號",
        "lat": 22.754124,
        "lon": 121.15119,
        "phoneclass": null,
        "phone": "0973-183-855",
        "stype": null,
        "goodstype": 253,
        "lineUrl": null,
        "memo": null,
        "status": 1,
        "updateid": null,
        "InsertDT": null,
        "UpdateDT": null,
        "SiteUrl": null,
        "IsWebSite": false,
        "IsCollege": false,
        "ApprovalNumber": null
    },
    {
        "SClassName": "循環概念店",
        "CityName": "臺東縣",
        "Zipcode": null,
        "AreaName": "臺東市",
        "STypeName": "捐送,買賣",
        "GoodsTypeName": "玩具類,書籍類,3C用品類,家具類,電器類,舊衣類,其他類,生活用品類",
        "StatusDesc": "營業中",
        "PhotoPath": "202211\\6f109411-8867-47b0-95fe-cda9da5a3dda.jpg",
        "StoreId_enc": "7wE8lgMhmcLRDizmBQokNwY1waaPyMHrOoaUnQJXFRek+NtVv6P5oDbVrPPbLjru",
        "storeid": "f05fe633-f654-4591-ba0f-c3967cc34088",
        "sname": "華山基金會台東卑南愛心天使站",
        "sclass": 2,
        "citycode": "V",
        "CodeZipIdx": 337,
        "addr": "開封街706號",
        "lat": 22.7593,
        "lon": 121.137925,
        "phoneclass": null,
        "phone": "089-340714",
        "stype": null,
        "goodstype": 255,
        "lineUrl": null,
        "memo": "https://www.facebook.com/954beinan/\n\n家具類僅收小型傢俱、護理用品(成人尿布)",
        "status": 1,
        "updateid": null,
        "InsertDT": null,
        "UpdateDT": null,
        "SiteUrl": null,
        "IsWebSite": false,
        "IsCollege": false,
        "ApprovalNumber": null
    },
    {
        "SClassName": "循環概念店",
        "CityName": "臺東縣",
        "Zipcode": null,
        "AreaName": "臺東市",
        "STypeName": "捐送,買賣",
        "GoodsTypeName": "玩具類,書籍類,3C用品類,電器類,舊衣類,其他類,生活用品類",
        "StatusDesc": "營業中",
        "PhotoPath": "202211\\0959f07b-9214-4e2d-8b46-7e8b058a4d51.jpg",
        "StoreId_enc": "1eTKdF9Jc7c7H0Cl9BkgSSbJyuGhxJ0bZJ3reFln9RpV8HebJSLU1qPCDGGgPe1k",
        "storeid": "78b6c10e-6a13-452d-b0d7-0510907cfe79",
        "sname": "財團法人李勝賢文教基金會",
        "sclass": 2,
        "citycode": "V",
        "CodeZipIdx": 337,
        "addr": "傳廣路153巷1號",
        "lat": 22.759526,
        "lon": 121.143563,
        "phoneclass": null,
        "phone": "089-361089，089-361899",
        "stype": null,
        "goodstype": 247,
        "lineUrl": null,
        "memo": "http://www.shanhsien.eoffering.org.tw ",
        "status": 1,
        "updateid": null,
        "InsertDT": null,
        "UpdateDT": null,
        "SiteUrl": null,
        "IsWebSite": false,
        "IsCollege": false,
        "ApprovalNumber": null
    },
    {
        "SClassName": "循環概念店",
        "CityName": "臺東縣",
        "Zipcode": null,
        "AreaName": "臺東市",
        "STypeName": "捐送,買賣",
        "GoodsTypeName": "玩具類,3C用品類,家具類,電器類,舊衣類,其他類,生活用品類",
        "StatusDesc": "營業中",
        "PhotoPath": "202211\\4b37e903-8ff8-4281-bba4-b2c7b1287b81.jpg",
        "StoreId_enc": "nybWngxRw9dqqzeu83pin8BQrvkebrlvbVi5uPtPy1KrsL4ndFpwBwG8Xyu7RCMq",
        "storeid": "e40fd2de-07ba-479f-ab94-fa08579503c6",
        "sname": "財團法人臺東縣私立牧心智能發展中心",
        "sclass": 2,
        "citycode": "V",
        "CodeZipIdx": 337,
        "addr": "民航路21號",
        "lat": 22.766582,
        "lon": 121.120891,
        "phoneclass": null,
        "phone": "089-237121",
        "stype": null,
        "goodstype": 253,
        "lineUrl": null,
        "memo": "http://www.mindfarm.org.tw 家具類僅收小型傢俱",
        "status": 1,
        "updateid": null,
        "InsertDT": null,
        "UpdateDT": null,
        "SiteUrl": null,
        "IsWebSite": false,
        "IsCollege": false,
        "ApprovalNumber": null
    },
    {
        "SClassName": "循環概念店",
        "CityName": "臺東縣",
        "Zipcode": null,
        "AreaName": "臺東市",
        "STypeName": "捐送,買賣",
        "GoodsTypeName": "3C用品類,電器類,舊衣類,生活用品類",
        "StatusDesc": "營業中",
        "PhotoPath": "202211\\a5d96327-44b5-42a8-9969-48fc1fdc372e.jpg",
        "StoreId_enc": "eGXLxgihl1dRm/DHBuetehSZjdO/SW5TX3bJKHKgFd4koCwabfj/6ovtY6GiIJJk",
        "storeid": "233e7ddc-9d4d-47d8-bf58-13eda361f199",
        "sname": "愛加倍小舖-台東基督教醫院",
        "sclass": 2,
        "citycode": "V",
        "CodeZipIdx": 337,
        "addr": "開封街350號",
        "lat": 22.763821,
        "lon": 121.146016,
        "phoneclass": null,
        "phone": "089-310000",
        "stype": null,
        "goodstype": 180,
        "lineUrl": null,
        "memo": "http://www.tch.org.tw\n3C用品、電器類均屬小家電",
        "status": 1,
        "updateid": null,
        "InsertDT": null,
        "UpdateDT": null,
        "SiteUrl": null,
        "IsWebSite": false,
        "IsCollege": false,
        "ApprovalNumber": null
    },
    {
        "SClassName": "循環概念店",
        "CityName": "臺東縣",
        "Zipcode": null,
        "AreaName": "臺東市",
        "STypeName": "捐送",
        "GoodsTypeName": "玩具類,書籍類,3C用品類,家具類,電器類,舊衣類,其他類",
        "StatusDesc": "營業中",
        "PhotoPath": "202211\\f32fb215-fc37-4b69-aac9-945da7e59079.jpg",
        "StoreId_enc": "1XPDIddK+cPdY/OA6woPB0OFNXkMeuj5C2Kgpi6kNKvwJBdXMp8z6Bxdf7EXXvMW",
        "storeid": "13ed1333-7ba4-472b-8796-55c875418643",
        "sname": "菈菈瑪 菈瑪二手雜貨",
        "sclass": 2,
        "citycode": "V",
        "CodeZipIdx": 337,
        "addr": "杭州街48號",
        "lat": 22.758552,
        "lon": 121.146018,
        "phoneclass": null,
        "phone": "089-343727，089-222009",
        "stype": null,
        "goodstype": 127,
        "lineUrl": null,
        "memo": "家具類僅收小型傢俱",
        "status": 1,
        "updateid": null,
        "InsertDT": null,
        "UpdateDT": null,
        "SiteUrl": null,
        "IsWebSite": false,
        "IsCollege": false,
        "ApprovalNumber": null
    },
    {
        "SClassName": "循環概念店",
        "CityName": "臺東縣",
        "Zipcode": null,
        "AreaName": "臺東市",
        "STypeName": "買賣",
        "GoodsTypeName": "玩具類,書籍類,3C用品類,家具類,舊衣類,其他類",
        "StatusDesc": "營業中",
        "PhotoPath": "202211\\96f6d8ea-0c8d-4d6f-8569-db02713aa8ff.png",
        "StoreId_enc": "zdBqIicYfJJ1YPdySwz6Cu5Hvw7DSEA/P2iiKEriTUet01zFiH+KAgjdSbZEsIKA",
        "storeid": "133b7290-553b-42f3-8699-b3991308f6e0",
        "sname": "二手雜貨舖",
        "sclass": 2,
        "citycode": "V",
        "CodeZipIdx": 337,
        "addr": "新成街22號",
        "lat": 22.76961,
        "lon": 121.124384,
        "phoneclass": null,
        "phone": "089-222865",
        "stype": null,
        "goodstype": 111,
        "lineUrl": null,
        "memo": "家具類僅收小型傢俱\n骨董用品",
        "status": 1,
        "updateid": null,
        "InsertDT": null,
        "UpdateDT": null,
        "SiteUrl": null,
        "IsWebSite": false,
        "IsCollege": false,
        "ApprovalNumber": null
    },
    {
        "SClassName": "二手物市集",
        "CityName": "臺東縣",
        "Zipcode": null,
        "AreaName": "臺東市",
        "STypeName": "買賣",
        "GoodsTypeName": "玩具類,書籍類,3C用品類,家具類,電器類,舊衣類,其他類",
        "StatusDesc": "營業中",
        "PhotoPath": null,
        "StoreId_enc": "nj/8HxHoSrO2sdpEq4gAKYcvVIw0vWO/2tLUxvC2AqW47bwBldBybs+f1ucn4Xq2",
        "storeid": "ded2c049-8d18-48f1-9bb1-dea1c2365513",
        "sname": "鐵花村音樂聚落二手市集",
        "sclass": 4,
        "citycode": "V",
        "CodeZipIdx": 337,
        "addr": "新生路135巷26號",
        "lat": 22.75334,
        "lon": 121.14618,
        "phoneclass": null,
        "phone": "089-343393",
        "stype": null,
        "goodstype": 127,
        "lineUrl": null,
        "memo": "http://www.lovelytaiwan.org.tw",
        "status": 1,
        "updateid": null,
        "InsertDT": null,
        "UpdateDT": null,
        "SiteUrl": null,
        "IsWebSite": false,
        "IsCollege": false,
        "ApprovalNumber": null
    },
    {
        "SClassName": "循環概念店",
        "CityName": "臺東縣",
        "Zipcode": null,
        "AreaName": "成功鎮",
        "STypeName": "捐送",
        "GoodsTypeName": "玩具類,書籍類,3C用品類,家具類,電器類,舊衣類,其他類",
        "StatusDesc": "營業中",
        "PhotoPath": "202211\\31d5d9c9-49b5-486c-8a0d-d7d25e667f10.png",
        "StoreId_enc": "MGD+8PLPeT27gep0AyOOYHvr/wn9NMo7PisxbI3+efTU22rG5lMx+uDRDdK7/vrv",
        "storeid": "0b744a64-a411-4d39-9103-e70550b1789b",
        "sname": "華山基金會成功愛心天使站",
        "sclass": 2,
        "citycode": "V",
        "CodeZipIdx": 338,
        "addr": "民生路115號",
        "lat": 23.101851,
        "lon": 121.379254,
        "phoneclass": null,
        "phone": "089-854930",
        "stype": null,
        "goodstype": 127,
        "lineUrl": null,
        "memo": "http://www.elder.org.tw 家具類僅收小型傢俱",
        "status": 1,
        "updateid": null,
        "InsertDT": null,
        "UpdateDT": null,
        "SiteUrl": null,
        "IsWebSite": false,
        "IsCollege": false,
        "ApprovalNumber": null
    },
    {
        "SClassName": "循環概念店",
        "CityName": "臺東縣",
        "Zipcode": null,
        "AreaName": "大武鄉",
        "STypeName": "捐送",
        "GoodsTypeName": "玩具類,書籍類,3C用品類,電器類,舊衣類,其他類",
        "StatusDesc": "營業中",
        "PhotoPath": null,
        "StoreId_enc": "BqdOoi9bgBJpo7o780u1FcPyQ3rnabMwpyxHXblE6gspoVVezm2LeLbU6ZhKx11q",
        "storeid": "3f558bf1-1809-4a4b-7f4b-08db80ef9990",
        "sname": "弱勢者關懷協會-新生活之家大武館",
        "sclass": 2,
        "citycode": "V",
        "CodeZipIdx": 341,
        "addr": "大武鄉大武村大武街108號",
        "lat": 22.35721,
        "lon": 120.90403,
        "phoneclass": null,
        "phone": "089-790073",
        "stype": null,
        "goodstype": 119,
        "lineUrl": null,
        "memo": "",
        "status": 1,
        "updateid": null,
        "InsertDT": null,
        "UpdateDT": null,
        "SiteUrl": "",
        "IsWebSite": false,
        "IsCollege": false,
        "ApprovalNumber": ""
    },
    {
        "SClassName": "循環概念店",
        "CityName": "臺東縣",
        "Zipcode": null,
        "AreaName": "大武鄉",
        "STypeName": "捐送",
        "GoodsTypeName": "玩具類,書籍類,3C用品類,電器類,舊衣類",
        "StatusDesc": "營業中",
        "PhotoPath": null,
        "StoreId_enc": "C+uIjk007DAu1gTI3RTIrLwPjsj3hhjt4MXuZ/lwlytqDVMjuD1qfhKH/c54D7Bo",
        "storeid": "65f362f7-0a2e-400f-7f4c-08db80ef9990",
        "sname": "台東家扶中心-大武服務處",
        "sclass": 2,
        "citycode": "V",
        "CodeZipIdx": 341,
        "addr": "大武村大武街109號",
        "lat": 22.35705,
        "lon": 120.90384,
        "phoneclass": null,
        "phone": "089-792747",
        "stype": null,
        "goodstype": 55,
        "lineUrl": null,
        "memo": "",
        "status": 1,
        "updateid": null,
        "InsertDT": null,
        "UpdateDT": null,
        "SiteUrl": "",
        "IsWebSite": false,
        "IsCollege": false,
        "ApprovalNumber": ""
    },
    {
        "SClassName": "循環概念店",
        "CityName": "臺東縣",
        "Zipcode": null,
        "AreaName": "大武鄉",
        "STypeName": "捐送,買賣",
        "GoodsTypeName": "玩具類,書籍類,3C用品類,電器類,舊衣類,其他類",
        "StatusDesc": "營業中",
        "PhotoPath": null,
        "StoreId_enc": "KT7xMgH5ZvF8fQLu+dHyueIcZ6La3rt3iIZfqeft1Z2T4NZBhJn/7ND0UdjllcUO",
        "storeid": "6b63bf4c-0dfa-4b17-7f4d-08db80ef9990",
        "sname": "中華基督教得勝教會",
        "sclass": 2,
        "citycode": "V",
        "CodeZipIdx": 341,
        "addr": "南興村達興150號",
        "lat": 22.31085,
        "lon": 120.88793,
        "phoneclass": null,
        "phone": "089-702732",
        "stype": null,
        "goodstype": 119,
        "lineUrl": null,
        "memo": "",
        "status": 1,
        "updateid": null,
        "InsertDT": null,
        "UpdateDT": null,
        "SiteUrl": "",
        "IsWebSite": false,
        "IsCollege": false,
        "ApprovalNumber": ""
    },
    {
        "SClassName": "循環概念店",
        "CityName": "臺東縣",
        "Zipcode": null,
        "AreaName": "大武鄉",
        "STypeName": "捐送,買賣",
        "GoodsTypeName": "玩具類,書籍類,3C用品類,電器類,舊衣類,其他類",
        "StatusDesc": "營業中",
        "PhotoPath": null,
        "StoreId_enc": "5/QfaombqkgApmjYPnBEA2+R1rf3EylTJfhxiY3smB6HGQm4M8XBeuK/DxKWNLQA",
        "storeid": "4cd1b22b-70c3-4462-7f4e-08db80ef9990",
        "sname": "大武天主堂",
        "sclass": 2,
        "citycode": "V",
        "CodeZipIdx": 341,
        "addr": "大武村大武街保安巷2號",
        "lat": 22.36369,
        "lon": 120.90675,
        "phoneclass": null,
        "phone": "089-791277",
        "stype": null,
        "goodstype": 119,
        "lineUrl": null,
        "memo": "",
        "status": 1,
        "updateid": null,
        "InsertDT": null,
        "UpdateDT": null,
        "SiteUrl": "",
        "IsWebSite": false,
        "IsCollege": false,
        "ApprovalNumber": ""
    },
    {
        "SClassName": "循環概念店",
        "CityName": "臺東縣",
        "Zipcode": null,
        "AreaName": "大武鄉",
        "STypeName": "捐送,買賣",
        "GoodsTypeName": "玩具類,書籍類,3C用品類,電器類,舊衣類,其他類",
        "StatusDesc": "營業中",
        "PhotoPath": null,
        "StoreId_enc": "UviPOvSL57dheQutjDwoKt4Yu7qxw03SL8AABWE2PqgV39uGf6OzGyBmObNehvYb",
        "storeid": "5836e12a-bb2d-4644-7f4f-08db80ef9990",
        "sname": "大武靈糧堂",
        "sclass": 2,
        "citycode": "V",
        "CodeZipIdx": 341,
        "addr": "大武村民族街45-1號",
        "lat": 22.3647,
        "lon": 120.90434,
        "phoneclass": null,
        "phone": "089-790345",
        "stype": null,
        "goodstype": 119,
        "lineUrl": null,
        "memo": "",
        "status": 1,
        "updateid": null,
        "InsertDT": null,
        "UpdateDT": null,
        "SiteUrl": "",
        "IsWebSite": false,
        "IsCollege": false,
        "ApprovalNumber": ""
    },
    {
        "SClassName": "循環概念店",
        "CityName": "臺東縣",
        "Zipcode": null,
        "AreaName": "太麻里鄉",
        "STypeName": "捐送",
        "GoodsTypeName": "玩具類,書籍類,3C用品類,家具類,電器類,舊衣類,其他類",
        "StatusDesc": "營業中",
        "PhotoPath": "202211\\ae6df3eb-e0be-4fa8-928d-7b1678547f1d.jpg",
        "StoreId_enc": "GdvJBFCxjvMXyy3L8O9aV3nRO4Ewu5uDD+GZ6/GfCGh7I3xJmkkyyTKVaQ12BcbL",
        "storeid": "b2757542-2010-4fe4-855f-885fe51da099",
        "sname": "華山基金會太麻里愛心天使站",
        "sclass": 2,
        "citycode": "V",
        "CodeZipIdx": 342,
        "addr": "外環路58號",
        "lat": 22.611971,
        "lon": 121.006766,
        "phoneclass": null,
        "phone": "089-782790",
        "stype": null,
        "goodstype": 127,
        "lineUrl": null,
        "memo": "http://www.elder.org.tw 家具類僅收小型傢俱",
        "status": 1,
        "updateid": null,
        "InsertDT": null,
        "UpdateDT": null,
        "SiteUrl": null,
        "IsWebSite": false,
        "IsCollege": false,
        "ApprovalNumber": null
    },
    {
        "SClassName": "二手物市集",
        "CityName": "臺東縣",
        "Zipcode": null,
        "AreaName": "東河鄉",
        "STypeName": "捐送,買賣",
        "GoodsTypeName": "玩具類,書籍類,電器類,舊衣類,其他類,生活用品類",
        "StatusDesc": "營業中",
        "PhotoPath": null,
        "StoreId_enc": "Ab0VLmXMRSf9Q/XVW6rye0tluwAONtAiPXi+WhWJCjQ2DuOvLdnffqAjpptOHh/K",
        "storeid": "c040aaf4-c66a-400a-d915-08dbd6cc43e1",
        "sname": "Dulan Flea Market 都蘭二手免廢市集(https://reurl.cc/77OzM1)",
        "sclass": 4,
        "citycode": "V",
        "CodeZipIdx": 343,
        "addr": "都蘭村372號(詳細位置請詳https://reurl.cc/77OzM1)",
        "lat": 22.87642,
        "lon": 121.22749,
        "phoneclass": null,
        "phone": "0936-422753",
        "stype": null,
        "goodstype": 243,
        "lineUrl": null,
        "memo": "都蘭二手免廢市集 永續社區日 二手店家地圖連結網址\nhttps://reurl.cc/77OzM1\n\n此地圖上的地點大部分為住家住址，每個月第一個星期六(10:00至16:00)如店家有於門口擺設「都蘭二手免廢市集 永續社區日」即為分享店家。",
        "status": 1,
        "updateid": null,
        "InsertDT": null,
        "UpdateDT": null,
        "SiteUrl": null,
        "IsWebSite": false,
        "IsCollege": false,
        "ApprovalNumber": null
    },
    {
        "SClassName": "循環概念店",
        "CityName": "臺東縣",
        "Zipcode": null,
        "AreaName": "鹿野鄉",
        "STypeName": "捐送",
        "GoodsTypeName": "玩具類,書籍類,3C用品類,家具類,電器類,舊衣類,其他類",
        "StatusDesc": "營業中",
        "PhotoPath": "202211\\0ec573e4-f0f2-44fe-9f24-d52bc0e620fc.png",
        "StoreId_enc": "gKk8yJbVk+8MlQ5bahiFqObC8XeEW1n5pwdEvXsobCNWGDWjIjg4YHZQ5g8uE1pA",
        "storeid": "26df2f99-d3c7-4cd9-ae13-76f34d4da89a",
        "sname": "華山基金會鹿野愛心天使站",
        "sclass": 2,
        "citycode": "V",
        "CodeZipIdx": 345,
        "addr": "中華路二段145號",
        "lat": 22.914812,
        "lon": 121.136545,
        "phoneclass": null,
        "phone": "089-551417",
        "stype": null,
        "goodstype": 127,
        "lineUrl": null,
        "memo": "https://www.facebook.com/login/?next=https%3A%2F%2Fwww.facebook.com%2FLuye955%2F\r\n家具類僅收小型傢俱",
        "status": 1,
        "updateid": null,
        "InsertDT": null,
        "UpdateDT": null,
        "SiteUrl": null,
        "IsWebSite": false,
        "IsCollege": false,
        "ApprovalNumber": null
    }
]